{
  "room": {
    "room_id": "room_1",
    "name": "Main",
    "polygon_mm": [
      {"x": 0, "y": 0},
      {"x": 6000, "y": 0},
      {"x": 6000, "y": 4000},
      {"x": 0, "y": 4000}
    ]
  },
  "walls": [
    {"wall_id": "wall_1", "p1_mm": {"x": 0, "y": 0}, "p2_mm": {"x": 6000, "y": 0}, "thickness_mm": 200},
    {"wall_id": "wall_2", "p1_mm": {"x": 6000, "y": 0}, "p2_mm": {"x": 6000, "y": 4000}, "thickness_mm": 200},
    {"wall_id": "wall_3", "p1_mm": {"x": 6000, "y": 4000}, "p2_mm": {"x": 0, "y": 4000}, "thickness_mm": 200},
    {"wall_id": "wall_4", "p1_mm": {"x": 0, "y": 4000}, "p2_mm": {"x": 0, "y": 0}, "thickness_mm": 200}
  ],
  "openings": {
    "doors": [
      {
        "door_id": "door_1",
        "wall_id": "wall_4",
        "start_mm": {"x": 0, "y": 1600},
        "end_mm": {"x": 0, "y": 2600},
        "leaf_width_mm": 900,
        "hinge_side": "left",
        "open_direction": "in",
        "open_angle_deg": 90
      }
    ],
    "windows": [
      {
        "window_id": "window_1",
        "wall_id": "wall_1",
        "start_mm": {"x": 2000, "y": 0},
        "end_mm": {"x": 4000, "y": 0},
        "sill_height_mm": 900,
        "height_mm": 1200
      }
    ]
  }
}
